licensespring/__init__.py
licensespring/api/__init__.py
licensespring/api/authorization.py
licensespring/api/error.py
licensespring/api/signature.py
licensespring/floating_server/__init__.py
licensespring/hardware/__init__.py
licensespring/licensefile/__init__.py
licensespring/licensefile/base_manager.py
licensespring/licensefile/bundle_manager.py
licensespring/licensefile/config.py
licensespring/licensefile/customer.py
licensespring/licensefile/data_storage.py
licensespring/licensefile/default_crypto.py
licensespring/licensefile/device_variables.py
licensespring/licensefile/error.py
licensespring/licensefile/feature_manager.py
licensespring/licensefile/floating_manager.py
licensespring/licensefile/helpers.py
licensespring/licensefile/license_data.py
licensespring/licensefile/license_manager.py
licensespring/licensefile/offline_activation_guard.py
licensespring/licensefile/product_details.py
licensespring/licensefile/service.py
licensespring/watchdog/__init__.py
licensespring/webhook/__init__.py
licensespring/webhook/error.py
licensespring/webhook/signature.py
licensespring/webhook/utils.py
licensespring-3.10.0.dist-info/LICENSE
licensespring-3.10.0.dist-info/METADATA
licensespring-3.10.0.dist-info/WHEEL
licensespring-3.10.0.dist-info/RECORD
