Metadata-Version: 2.3
Name: licensespring
Version: 3.10.0
Summary: LicenseSpring Python Library
License: LicenseSpring SDK Source Code License (LSSCL)
Author: Toni Sredanović
Author-email: toni@licensespring.com
Requires-Python: >=3.10,<4.0
Classifier: License :: Other/Proprietary License
Classifier: Operating System :: OS Independent
Classifier: Programming Language :: Python :: 3
Classifier: Programming Language :: Python :: 3.10
Classifier: Programming Language :: Python :: 3.11
Classifier: Programming Language :: Python :: 3.12
Classifier: Programming Language :: Python :: 3.13
Requires-Dist: licensespring-hardware-id-generator (>=1.1.0,<2.0.0)
Requires-Dist: pycryptodome (>=3.21.0,<4.0.0)
Requires-Dist: pyopenssl (>=25.3.0,<26.0.0)
Requires-Dist: requests (>=2.32.3,<3.0.0)
Requires-Dist: winregistry (>=2.1.0,<3.0.0)
Project-URL: Documentation, https://docs.licensespring.com/sdks/python
Project-URL: Homepage, https://licensespring.com/
